sphinxcontrib.readme_to_index-0.0.1-py3.7-nspkg.pth
sphinxcontrib/readme-to-index/__init__.py
sphinxcontrib/readme-to-index/implementation.py
sphinxcontrib.readme_to_index-0.0.1.dist-info/LICENSE
sphinxcontrib.readme_to_index-0.0.1.dist-info/METADATA
sphinxcontrib.readme_to_index-0.0.1.dist-info/WHEEL
sphinxcontrib.readme_to_index-0.0.1.dist-info/namespace_packages.txt
sphinxcontrib.readme_to_index-0.0.1.dist-info/top_level.txt
sphinxcontrib.readme_to_index-0.0.1.dist-info/RECORD
